README.rst
bootstrap.py
buildout.cfg
coolblue.zip
screenshot.png
setup.py
docs/HISTORY.txt
plonetheme/__init__.py
plonetheme.coolblue.egg-info/PKG-INFO
plonetheme.coolblue.egg-info/SOURCES.txt
plonetheme.coolblue.egg-info/dependency_links.txt
plonetheme.coolblue.egg-info/entry_points.txt
plonetheme.coolblue.egg-info/namespace_packages.txt
plonetheme.coolblue.egg-info/requires.txt
plonetheme.coolblue.egg-info/top_level.txt
plonetheme/coolblue/__init__.py
plonetheme/coolblue/configure.zcml
plonetheme/coolblue/theme/coolblue/index.html
plonetheme/coolblue/theme/coolblue/rules.xml
plonetheme/coolblue/theme/coolblue/static/css/coolblue.css
plonetheme/coolblue/theme/coolblue/static/css/enhancements.css
plonetheme/coolblue/theme/coolblue/static/css/reset.css
plonetheme/coolblue/theme/coolblue/static/css/screen.css
plonetheme/coolblue/theme/coolblue/static/images/bg.gif
plonetheme/coolblue/theme/coolblue/static/images/bg.jpg
plonetheme/coolblue/theme/coolblue/static/images/clock.gif
plonetheme/coolblue/theme/coolblue/static/images/comment.gif
plonetheme/coolblue/theme/coolblue/static/images/content.gif
plonetheme/coolblue/theme/coolblue/static/images/current.gif
plonetheme/coolblue/theme/coolblue/static/images/current.jpg
plonetheme/coolblue/theme/coolblue/static/images/date-bg.gif
plonetheme/coolblue/theme/coolblue/static/images/delicious_32.png
plonetheme/coolblue/theme/coolblue/static/images/digg_32.png
plonetheme/coolblue/theme/coolblue/static/images/document.gif
plonetheme/coolblue/theme/coolblue/static/images/email_32.png
plonetheme/coolblue/theme/coolblue/static/images/facebook_32.png
plonetheme/coolblue/theme/coolblue/static/images/firefox-gray.jpg
plonetheme/coolblue/theme/coolblue/static/images/footer-line.gif
plonetheme/coolblue/theme/coolblue/static/images/gravatar.jpg
plonetheme/coolblue/theme/coolblue/static/images/header-bg.jpg
plonetheme/coolblue/theme/coolblue/static/images/header-bg.png
plonetheme/coolblue/theme/coolblue/static/images/img-post.jpg
plonetheme/coolblue/theme/coolblue/static/images/linkedin_32.png
plonetheme/coolblue/theme/coolblue/static/images/newsvine_32.png
plonetheme/coolblue/theme/coolblue/static/images/permalink.gif
plonetheme/coolblue/theme/coolblue/static/images/quote.gif
plonetheme/coolblue/theme/coolblue/static/images/rss.gif
