Metadata-Version: 1.0
Name: plonetheme.coolblue
Version: 0.1.1
Summary: An installable Diazo theme for Plone 4.1
Home-page: https://github.com/collective/plonetheme.coolblue
Author: Alex Clark
Author-email: aclark@aclark.net
License: UNKNOWN
Platform: UNKNOWN
Classifier: Framework :: Plone
Classifier: Programming Language :: Python
